supadef/__init__.py
supadef/cli.py
supadef/config.py
supadef/credentials.py
supadef/filesystem.py
supadef/links.py
supadef/logger.py
supadef/network.py
supadef/platform.py
supadef/push.py
supadef/util.py
supadef/version.py
supadef-0.0.66.dist-info/licenses/LICENSE
supadef-0.0.66.dist-info/METADATA
supadef-0.0.66.dist-info/WHEEL
supadef-0.0.66.dist-info/entry_points.txt
supadef-0.0.66.dist-info/top_level.txt
supadef-0.0.66.dist-info/RECORD
