Metadata-Version: 2.4
Name: supadef
Version: 0.0.66
Summary: Official command-line interface for supadef ⚡️
Author-email: Connor McLaughlin <connor@fractall.com>
Project-URL: Homepage, https://github.com/connormcl/supadef_cli
Project-URL: Bug Tracker, https://github.com/connormcl/supadef_cli/issues
Classifier: Programming Language :: Python :: 3
Requires-Python: >=3.7
License-File: LICENSE
Requires-Dist: typer>=0.7.0
Requires-Dist: requests>=2.28.2
Requires-Dist: twine>=4.0.2
Requires-Dist: pyyaml>=6.0
Requires-Dist: pytest>=7.2.1
Requires-Dist: tabulate>=0.9.0
Requires-Dist: yaspin>=3.0.1
Requires-Dist: pydantic>=2.0.0
Requires-Dist: pathspec>=0.12.1
Requires-Dist: orjson<4,>=3.10
Requires-Dist: rich>=14.0.0
Requires-Dist: build
Requires-Dist: twine
Dynamic: license-file
